emoji_translate/__init__.py
emoji_translate/emoji_translate.py
emoji_translate/data/__init__.py
emoji_translate/data/emoji_utf8_lexicon.txt
emoji_translate/data/emojis.json
emoji_translate/data/merge.py
emoji_translate/data/merged_emojis.json
tests/__init__.py
tests/test_emoji_translate.py
emoji_translate-0.1.1.dist-info/LICENSE
emoji_translate-0.1.1.dist-info/METADATA
emoji_translate-0.1.1.dist-info/WHEEL
emoji_translate-0.1.1.dist-info/top_level.txt
emoji_translate-0.1.1.dist-info/zip-safe
emoji_translate-0.1.1.dist-info/RECORD
