Metadata-Version: 2.1
Name: emoji-translate
Version: 0.1.1
Summary: Emoji translation for Python
Home-page: https://github.com/fabriceyhc/emoji_translate
Author: Fabrice Harel-Canada
Author-email: fabriceyhc@gmail.com
License: MIT
Keywords: emoji,translate,emoji_translate
Classifier: Intended Audience :: Developers
Classifier: Intended Audience :: Information Technology
Classifier: License :: OSI Approved :: BSD License
Classifier: Operating System :: OS Independent
Classifier: Programming Language :: Python :: 2
Classifier: Programming Language :: Python :: 2.7
Classifier: Programming Language :: Python :: 3
Classifier: Programming Language :: Python :: 3.4
Classifier: Programming Language :: Python :: 3.5
Classifier: Programming Language :: Python :: 3.6
Classifier: Programming Language :: Python :: 3.7
Classifier: Programming Language :: Python :: Implementation :: CPython
Classifier: Programming Language :: Python :: Implementation :: PyPy
Classifier: Programming Language :: Python
Classifier: Topic :: Internet :: WWW/HTTP :: Dynamic Content
Classifier: Topic :: Multimedia :: Graphics :: Presentation
Classifier: Topic :: Software Development :: Libraries :: Python Modules
License-File: LICENSE
Requires-Dist: emoji (==1.7.0)
Requires-Dist: pandas
Requires-Dist: numpy
